facebook/__init__.py
facebook/version.py
kedo_facebook_sdk-1.0.0.0.1.dist-info/DESCRIPTION.rst
kedo_facebook_sdk-1.0.0.0.1.dist-info/METADATA
kedo_facebook_sdk-1.0.0.0.1.dist-info/RECORD
kedo_facebook_sdk-1.0.0.0.1.dist-info/WHEEL
kedo_facebook_sdk-1.0.0.0.1.dist-info/metadata.json
kedo_facebook_sdk-1.0.0.0.1.dist-info/top_level.txt
